{
  "annotations": {
    "list": [
      {
        "builtIn": 1,
        "datasource": {
          "type": "prometheus",
          "uid": "prometheus"
        },
        "enable": true,
        "hide": true,
        "iconColor": "rgba(0, 211, 255, 1)",
        "name": "Annotations & Alerts",
        "type": "dashboard"
      }
    ]
  },
  "description": "Graphs ZFS ARC and ARC L2 Hit %, Hits, Misses, Size, and Zpool",
  "editable": true,
  "fiscalYearStartMonth": 0,
  "graphTooltip": 0,
  "id": 49,
  "links": [],
  "panels": [
    {
      "collapsed": false,
      "gridPos": {
        "h": 1,
        "w": 24,
        "x": 0,
        "y": 0
      },
      "id": 26,
      "panels": [],
      "title": "Pools",
      "type": "row"
    },
    {
      "datasource": {
        "type": "prometheus",
        "uid": "prometheus"
      },
      "fieldConfig": {
        "defaults": {
          "color": {
            "mode": "palette-classic"
          },
          "custom": {
            "axisBorderShow": false,
            "axisCenteredZero": false,
            "axisColorMode": "text",
            "axisLabel": "",
            "axisPlacement": "auto",
            "barAlignment": 0,
            "barWidthFactor": 0.6,
            "drawStyle": "line",
            "fillOpacity": 10,
            "gradientMode": "none",
            "hideFrom": {
              "legend": false,
              "tooltip": false,
              "viz": false
            },
            "insertNulls": false,
            "lineInterpolation": "linear",
            "lineWidth": 1,
            "pointSize": 5,
            "scaleDistribution": {
              "type": "linear"
            },
            "showPoints": "never",
            "spanNulls": false,
            "stacking": {
              "group": "A",
              "mode": "none"
            },
            "thresholdsStyle": {
              "mode": "off"
            }
          },
          "mappings": [],
          "thresholds": {
            "mode": "absolute",
            "steps": [
              {
                "color": "green",
                "value": 0
              },
              {
                "color": "red",
                "value": 80
              }
            ]
          },
          "unit": "ns"
        },
        "overrides": []
      },
      "gridPos": {
        "h": 7,
        "w": 12,
        "x": 0,
        "y": 1
      },
      "id": 19,
      "options": {
        "dataLinks": [],
        "legend": {
          "calcs": [
            "mean",
            "lastNotNull",
            "max",
            "min"
          ],
          "displayMode": "table",
          "placement": "right",
          "showLegend": true,
          "width": 350
        },
        "tooltip": {
          "hideZeros": false,
          "mode": "multi",
          "sort": "desc"
        }
      },
      "pluginVersion": "12.1.0",
      "targets": [
        {
          "datasource": {
            "type": "prometheus",
            "uid": "prometheus"
          },
          "editorMode": "code",
          "expr": "irate(node_zfs_zpool_rtime{job=\"node-exporter\",kubernetes_node=\"$node\"}[5m])",
          "format": "time_series",
          "intervalFactor": 2,
          "legendFormat": "{{zpool}} - read",
          "range": true,
          "refId": "A",
          "step": 2,
          "target": ""
        },
        {
          "datasource": {
            "type": "prometheus",
            "uid": "prometheus"
          },
          "editorMode": "code",
          "expr": "irate(node_zfs_zpool_wtime{job=\"node-exporter\",kubernetes_node=~\"$node\"}[5m])",
          "format": "time_series",
          "hide": false,
          "intervalFactor": 2,
          "legendFormat": "{{zpool}} - write",
          "range": true,
          "refId": "B",
          "step": 2,
          "target": ""
        }
      ],
      "title": "ZPOOL - Time",
      "type": "timeseries"
    },
    {
      "datasource": {
        "type": "prometheus",
        "uid": "prometheus"
      },
      "fieldConfig": {
        "defaults": {
          "color": {
            "mode": "palette-classic"
          },
          "custom": {
            "axisBorderShow": false,
            "axisCenteredZero": false,
            "axisColorMode": "text",
            "axisLabel": "",
            "axisPlacement": "auto",
            "barAlignment": 0,
            "barWidthFactor": 0.6,
            "drawStyle": "line",
            "fillOpacity": 10,
            "gradientMode": "none",
            "hideFrom": {
              "legend": false,
              "tooltip": false,
              "viz": false
            },
            "insertNulls": false,
            "lineInterpolation": "linear",
            "lineWidth": 1,
            "pointSize": 5,
            "scaleDistribution": {
              "type": "linear"
            },
            "showPoints": "never",
            "spanNulls": false,
            "stacking": {
              "group": "A",
              "mode": "none"
            },
            "thresholdsStyle": {
              "mode": "off"
            }
          },
          "mappings": [],
          "thresholds": {
            "mode": "absolute",
            "steps": [
              {
                "color": "green",
                "value": 0
              },
              {
                "color": "red",
                "value": 80
              }
            ]
          },
          "unit": "none"
        },
        "overrides": []
      },
      "gridPos": {
        "h": 7,
        "w": 12,
        "x": 12,
        "y": 1
      },
      "id": 20,
      "options": {
        "dataLinks": [],
        "legend": {
          "calcs": [
            "max",
            "min",
            "sum"
          ],
          "displayMode": "table",
          "placement": "right",
          "showLegend": true,
          "width": 350
        },
        "tooltip": {
          "hideZeros": false,
          "mode": "multi",
          "sort": "desc"
        }
      },
      "pluginVersion": "12.1.0",
      "targets": [
        {
          "datasource": {
            "type": "prometheus",
            "uid": "prometheus"
          },
          "editorMode": "code",
          "expr": "irate(node_zfs_zpool_dataset_reads{job=\"node-exporter\",kubernetes_node=~\"$node\"}[5m])",
          "format": "time_series",
          "intervalFactor": 2,
          "legendFormat": "{{zpool}} - reads",
          "range": true,
          "refId": "A",
          "step": 2,
          "target": ""
        },
        {
          "datasource": {
            "type": "prometheus",
            "uid": "prometheus"
          },
          "editorMode": "code",
          "expr": "irate(node_zfs_zpool_dataset_writes{job=\"node-exporter\",kubernetes_node=~\"$node\"}[5m])",
          "format": "time_series",
          "intervalFactor": 2,
          "legendFormat": "{{zpool}} - writes",
          "range": true,
          "refId": "B",
          "step": 2,
          "target": ""
        }
      ],
      "title": "ZPOOL - Ops",
      "type": "timeseries"
    },
    {
      "collapsed": false,
      "gridPos": {
        "h": 1,
        "w": 24,
        "x": 0,
        "y": 8
      },
      "id": 24,
      "panels": [],
      "title": "ARC",
      "type": "row"
    },
    {
      "datasource": {
        "type": "prometheus",
        "uid": "prometheus"
      },
      "fieldConfig": {
        "defaults": {
          "color": {
            "mode": "palette-classic"
          },
          "custom": {
            "axisBorderShow": false,
            "axisCenteredZero": false,
            "axisColorMode": "text",
            "axisLabel": "",
            "axisPlacement": "auto",
            "barAlignment": 0,
            "barWidthFactor": 0.6,
            "drawStyle": "line",
            "fillOpacity": 10,
            "gradientMode": "none",
            "hideFrom": {
              "legend": false,
              "tooltip": false,
              "viz": false
            },
            "insertNulls": false,
            "lineInterpolation": "linear",
            "lineWidth": 1,
            "pointSize": 5,
            "scaleDistribution": {
              "type": "linear"
            },
            "showPoints": "never",
            "spanNulls": false,
            "stacking": {
              "group": "A",
              "mode": "none"
            },
            "thresholdsStyle": {
              "mode": "off"
            }
          },
          "mappings": [],
          "thresholds": {
            "mode": "absolute",
            "steps": [
              {
                "color": "green",
                "value": 0
              },
              {
                "color": "red",
                "value": 80
              }
            ]
          },
          "unit": "percent"
        },
        "overrides": []
      },
      "gridPos": {
        "h": 6,
        "w": 12,
        "x": 0,
        "y": 9
      },
      "id": 14,
      "options": {
        "dataLinks": [],
        "legend": {
          "calcs": [
            "mean"
          ],
          "displayMode": "list",
          "placement": "bottom",
          "showLegend": true,
          "width": 350
        },
        "tooltip": {
          "hideZeros": false,
          "mode": "multi",
          "sort": "desc"
        }
      },
      "pluginVersion": "12.1.0",
      "targets": [
        {
          "datasource": {
            "type": "prometheus",
            "uid": "prometheus"
          },
          "editorMode": "code",
          "expr": "irate(node_zfs_arc_demand_data_hits{job=\"node-exporter\",kubernetes_node=~\"$node\"}[5m]) / (irate(node_zfs_arc_demand_data_hits{job=\"node-exporter\",kubernetes_node=~\"$node\"}[5m]) + irate(node_zfs_arc_demand_data_misses{job=\"node-exporter\",kubernetes_node=~\"$node\"}[5m])) * 100",
          "format": "time_series",
          "intervalFactor": 2,
          "legendFormat": "data",
          "range": true,
          "refId": "A",
          "step": 2,
          "target": ""
        },
        {
          "datasource": {
            "type": "prometheus",
            "uid": "prometheus"
          },
          "expr": "irate(node_zfs_arc_demand_metadata_hits{job=\"node-exporter\",instance=~\"$node:$port\"}[5m]) / (irate(node_zfs_arc_demand_metadata_hits{job=\"node-exporter\",instance=~\"$node:$port\"}[5m]) + irate(node_zfs_arc_demand_metadata_misses{job=\"node-exporter\",instance=~\"$node:$port\"}[5m])) * 100",
          "format": "time_series",
          "intervalFactor": 2,
          "legendFormat": "metadata",
          "refId": "B",
          "step": 2,
          "target": ""
        }
      ],
      "title": "ARC - Hit %",
      "type": "timeseries"
    },
    {
      "datasource": {
        "type": "prometheus",
        "uid": "prometheus"
      },
      "fieldConfig": {
        "defaults": {
          "color": {
            "mode": "palette-classic"
          },
          "custom": {
            "axisBorderShow": false,
            "axisCenteredZero": false,
            "axisColorMode": "text",
            "axisLabel": "",
            "axisPlacement": "auto",
            "barAlignment": 0,
            "barWidthFactor": 0.6,
            "drawStyle": "line",
            "fillOpacity": 10,
            "gradientMode": "none",
            "hideFrom": {
              "legend": false,
              "tooltip": false,
              "viz": false
            },
            "insertNulls": false,
            "lineInterpolation": "linear",
            "lineWidth": 1,
            "pointSize": 5,
            "scaleDistribution": {
              "type": "linear"
            },
            "showPoints": "never",
            "spanNulls": false,
            "stacking": {
              "group": "A",
              "mode": "none"
            },
            "thresholdsStyle": {
              "mode": "off"
            }
          },
          "mappings": [],
          "thresholds": {
            "mode": "absolute",
            "steps": [
              {
                "color": "green",
                "value": 0
              },
              {
                "color": "red",
                "value": 80
              }
            ]
          },
          "unit": "none"
        },
        "overrides": []
      },
      "gridPos": {
        "h": 6,
        "w": 12,
        "x": 12,
        "y": 9
      },
      "id": 13,
      "options": {
        "dataLinks": [],
        "legend": {
          "calcs": [
            "sum"
          ],
          "displayMode": "list",
          "placement": "bottom",
          "showLegend": true,
          "width": 350
        },
        "tooltip": {
          "hideZeros": false,
          "mode": "multi",
          "sort": "desc"
        }
      },
      "pluginVersion": "12.1.0",
      "targets": [
        {
          "datasource": {
            "type": "prometheus",
            "uid": "prometheus"
          },
          "editorMode": "code",
          "expr": "irate(node_zfs_arc_demand_data_hits{job=\"node-exporter\",kubernetes_node=~\"$node\"}[5m])",
          "format": "time_series",
          "intervalFactor": 2,
          "legendFormat": "data_hits",
          "range": true,
          "refId": "A",
          "step": 2,
          "target": ""
        },
        {
          "datasource": {
            "type": "prometheus",
            "uid": "prometheus"
          },
          "editorMode": "code",
          "expr": "irate(node_zfs_arc_demand_metadata_hits{job=\"node-exporter\",kubernetes_node=~\"$node\"}[5m])",
          "format": "time_series",
          "intervalFactor": 2,
          "legendFormat": "metadata_hits",
          "range": true,
          "refId": "B",
          "step": 2,
          "target": ""
        },
        {
          "datasource": {
            "type": "prometheus",
            "uid": "prometheus"
          },
          "editorMode": "code",
          "expr": "irate(node_zfs_arc_demand_data_misses{job=\"node-exporter\",kubernetes_node=~\"$node\"}[5m])",
          "format": "time_series",
          "intervalFactor": 2,
          "legendFormat": "data_misses",
          "range": true,
          "refId": "C",
          "step": 2,
          "target": ""
        },
        {
          "datasource": {
            "type": "prometheus",
            "uid": "prometheus"
          },
          "editorMode": "code",
          "expr": "irate(node_zfs_arc_demand_metadata_misses{job=\"node-exporter\",kubernetes_node=~\"$node\"}[5m])",
          "format": "time_series",
          "intervalFactor": 2,
          "legendFormat": "metadata_misses",
          "range": true,
          "refId": "D",
          "step": 2,
          "target": ""
        }
      ],
      "title": "ARC - Hits, Misses",
      "type": "timeseries"
    },
    {
      "datasource": {
        "type": "prometheus",
        "uid": "prometheus"
      },
      "fieldConfig": {
        "defaults": {
          "color": {
            "mode": "palette-classic"
          },
          "custom": {
            "axisBorderShow": false,
            "axisCenteredZero": false,
            "axisColorMode": "text",
            "axisLabel": "",
            "axisPlacement": "auto",
            "barAlignment": 0,
            "barWidthFactor": 0.6,
            "drawStyle": "line",
            "fillOpacity": 10,
            "gradientMode": "none",
            "hideFrom": {
              "legend": false,
              "tooltip": false,
              "viz": false
            },
            "insertNulls": false,
            "lineInterpolation": "linear",
            "lineWidth": 1,
            "pointSize": 5,
            "scaleDistribution": {
              "type": "linear"
            },
            "showPoints": "never",
            "spanNulls": false,
            "stacking": {
              "group": "A",
              "mode": "normal"
            },
            "thresholdsStyle": {
              "mode": "off"
            }
          },
          "mappings": [],
          "thresholds": {
            "mode": "absolute",
            "steps": [
              {
                "color": "green",
                "value": 0
              },
              {
                "color": "red",
                "value": 80
              }
            ]
          },
          "unit": "bytes"
        },
        "overrides": []
      },
      "gridPos": {
        "h": 7,
        "w": 24,
        "x": 0,
        "y": 15
      },
      "id": 15,
      "options": {
        "dataLinks": [],
        "legend": {
          "calcs": [
            "mean",
            "lastNotNull",
            "max",
            "min"
          ],
          "displayMode": "table",
          "placement": "right",
          "showLegend": true,
          "width": 350
        },
        "tooltip": {
          "hideZeros": false,
          "mode": "multi",
          "sort": "desc"
        }
      },
      "pluginVersion": "12.1.0",
      "targets": [
        {
          "datasource": {
            "type": "prometheus",
            "uid": "prometheus"
          },
          "editorMode": "code",
          "expr": "node_zfs_arc_data_size{job=\"node-exporter\",kubernetes_node=~\"$node\"}",
          "format": "time_series",
          "hide": false,
          "interval": "",
          "intervalFactor": 2,
          "legendFormat": "data",
          "range": true,
          "refId": "I",
          "step": 2,
          "target": ""
        },
        {
          "datasource": {
            "type": "prometheus",
            "uid": "prometheus"
          },
          "editorMode": "code",
          "expr": "node_zfs_arc_metadata_size{job=\"node-exporter\",kubernetes_node=~\"$node\"}",
          "format": "time_series",
          "intervalFactor": 2,
          "legendFormat": "metadata",
          "range": true,
          "refId": "D",
          "step": 2,
          "target": ""
        },
        {
          "datasource": {
            "type": "prometheus",
            "uid": "prometheus"
          },
          "editorMode": "code",
          "expr": "node_zfs_arc_anon_size{job=\"node-exporter\",kubernetes_node=~\"$node\"}",
          "format": "time_series",
          "hide": false,
          "interval": "",
          "intervalFactor": 2,
          "legendFormat": "anon",
          "range": true,
          "refId": "B",
          "step": 2,
          "target": ""
        },
        {
          "datasource": {
            "type": "prometheus",
            "uid": "prometheus"
          },
          "editorMode": "code",
          "expr": "node_zfs_arc_hdr_size{job=\"node-exporter\",kubernetes_node=~\"$node\"}",
          "format": "time_series",
          "intervalFactor": 2,
          "legendFormat": "hdr",
          "range": true,
          "refId": "C",
          "step": 2,
          "target": ""
        },
        {
          "datasource": {
            "type": "prometheus",
            "uid": "prometheus"
          },
          "editorMode": "code",
          "expr": "node_zfs_arc_other_size{job=\"node-exporter\",kubernetes_node=~\"$node\"}",
          "format": "time_series",
          "intervalFactor": 2,
          "legendFormat": "other",
          "range": true,
          "refId": "J",
          "step": 2,
          "target": ""
        }
      ],
      "title": "ARC - Size",
      "type": "timeseries"
    },
    {
      "collapsed": false,
      "gridPos": {
        "h": 1,
        "w": 24,
        "x": 0,
        "y": 22
      },
      "id": 22,
      "panels": [],
      "title": "ARC L2",
      "type": "row"
    },
    {
      "datasource": {
        "type": "prometheus",
        "uid": "prometheus"
      },
      "fieldConfig": {
        "defaults": {
          "color": {
            "mode": "palette-classic"
          },
          "custom": {
            "axisBorderShow": false,
            "axisCenteredZero": false,
            "axisColorMode": "text",
            "axisLabel": "",
            "axisPlacement": "auto",
            "barAlignment": 0,
            "barWidthFactor": 0.6,
            "drawStyle": "line",
            "fillOpacity": 0,
            "gradientMode": "none",
            "hideFrom": {
              "legend": false,
              "tooltip": false,
              "viz": false
            },
            "insertNulls": false,
            "lineInterpolation": "linear",
            "lineWidth": 1,
            "pointSize": 5,
            "scaleDistribution": {
              "type": "linear"
            },
            "showPoints": "auto",
            "spanNulls": false,
            "stacking": {
              "group": "A",
              "mode": "none"
            },
            "thresholdsStyle": {
              "mode": "off"
            }
          },
          "mappings": [],
          "thresholds": {
            "mode": "absolute",
            "steps": [
              {
                "color": "green",
                "value": 0
              },
              {
                "color": "red",
                "value": 80
              }
            ]
          }
        },
        "overrides": []
      },
      "gridPos": {
        "h": 7,
        "w": 12,
        "x": 0,
        "y": 23
      },
      "id": 16,
      "options": {
        "dataLinks": [],
        "legend": {
          "calcs": [],
          "displayMode": "list",
          "placement": "bottom",
          "showLegend": true
        },
        "tooltip": {
          "hideZeros": false,
          "mode": "single",
          "sort": "none"
        }
      },
      "pluginVersion": "12.1.0",
      "targets": [
        {
          "datasource": {
            "type": "prometheus",
            "uid": "prometheus"
          },
          "editorMode": "code",
          "expr": "irate(node_zfs_arc_l2_hits{job=\"node-exporter\",kubernetes_node=~\"$node\"}[5m]) / (irate(node_zfs_arc_l2_hits{job=\"node-exporter\",kubernetes_node=~\"$node\"}[5m]) + irate(node_zfs_arc_l2_misses{job=\"node-exporter\",kubernetes_node=~\"$node\"}[5m])) * 100",
          "format": "time_series",
          "intervalFactor": 2,
          "legendFormat": "L2",
          "range": true,
          "refId": "A",
          "step": 2,
          "target": ""
        }
      ],
      "title": "ARC L2 - Hit %",
      "type": "timeseries"
    },
    {
      "datasource": {
        "type": "prometheus",
        "uid": "prometheus"
      },
      "fieldConfig": {
        "defaults": {
          "color": {
            "mode": "palette-classic"
          },
          "custom": {
            "axisBorderShow": false,
            "axisCenteredZero": false,
            "axisColorMode": "text",
            "axisLabel": "",
            "axisPlacement": "auto",
            "barAlignment": 0,
            "barWidthFactor": 0.6,
            "drawStyle": "line",
            "fillOpacity": 0,
            "gradientMode": "none",
            "hideFrom": {
              "legend": false,
              "tooltip": false,
              "viz": false
            },
            "insertNulls": false,
            "lineInterpolation": "linear",
            "lineWidth": 1,
            "pointSize": 5,
            "scaleDistribution": {
              "type": "linear"
            },
            "showPoints": "auto",
            "spanNulls": false,
            "stacking": {
              "group": "A",
              "mode": "none"
            },
            "thresholdsStyle": {
              "mode": "off"
            }
          },
          "mappings": [],
          "thresholds": {
            "mode": "absolute",
            "steps": [
              {
                "color": "green",
                "value": 0
              },
              {
                "color": "red",
                "value": 80
              }
            ]
          }
        },
        "overrides": []
      },
      "gridPos": {
        "h": 7,
        "w": 12,
        "x": 12,
        "y": 23
      },
      "id": 17,
      "options": {
        "dataLinks": [],
        "legend": {
          "calcs": [],
          "displayMode": "list",
          "placement": "bottom",
          "showLegend": true
        },
        "tooltip": {
          "hideZeros": false,
          "mode": "single",
          "sort": "none"
        }
      },
      "pluginVersion": "12.1.0",
      "targets": [
        {
          "datasource": {
            "type": "prometheus",
            "uid": "prometheus"
          },
          "editorMode": "code",
          "expr": "irate(node_zfs_arc_l2_hits{job=\"node-exporter\",kubernetes_node=~\"$node\"}[5m])",
          "format": "time_series",
          "intervalFactor": 2,
          "legendFormat": "hits",
          "range": true,
          "refId": "A",
          "step": 2,
          "target": ""
        },
        {
          "datasource": {
            "type": "prometheus",
            "uid": "prometheus"
          },
          "editorMode": "code",
          "expr": "irate(node_zfs_arc_l2_misses{job=\"node-exporter\",kubernetes_node=~\"$node\"}[5m])",
          "format": "time_series",
          "intervalFactor": 2,
          "legendFormat": "misses",
          "range": true,
          "refId": "B",
          "step": 2,
          "target": ""
        }
      ],
      "title": "ARC L2 - Hits, Misses",
      "type": "timeseries"
    },
    {
      "datasource": {
        "type": "prometheus",
        "uid": "prometheus"
      },
      "fieldConfig": {
        "defaults": {
          "color": {
            "mode": "palette-classic"
          },
          "custom": {
            "axisBorderShow": false,
            "axisCenteredZero": false,
            "axisColorMode": "text",
            "axisLabel": "",
            "axisPlacement": "auto",
            "barAlignment": 0,
            "barWidthFactor": 0.6,
            "drawStyle": "line",
            "fillOpacity": 0,
            "gradientMode": "none",
            "hideFrom": {
              "legend": false,
              "tooltip": false,
              "viz": false
            },
            "insertNulls": false,
            "lineInterpolation": "linear",
            "lineWidth": 1,
            "pointSize": 5,
            "scaleDistribution": {
              "type": "linear"
            },
            "showPoints": "auto",
            "spanNulls": false,
            "stacking": {
              "group": "A",
              "mode": "none"
            },
            "thresholdsStyle": {
              "mode": "off"
            }
          },
          "mappings": [],
          "thresholds": {
            "mode": "absolute",
            "steps": [
              {
                "color": "green",
                "value": 0
              },
              {
                "color": "red",
                "value": 80
              }
            ]
          }
        },
        "overrides": []
      },
      "gridPos": {
        "h": 7,
        "w": 24,
        "x": 0,
        "y": 30
      },
      "id": 18,
      "options": {
        "dataLinks": [],
        "legend": {
          "calcs": [],
          "displayMode": "list",
          "placement": "bottom",
          "showLegend": true
        },
        "tooltip": {
          "hideZeros": false,
          "mode": "single",
          "sort": "none"
        }
      },
      "pluginVersion": "12.1.0",
      "targets": [
        {
          "datasource": {
            "type": "prometheus",
            "uid": "prometheus"
          },
          "editorMode": "code",
          "expr": "node_zfs_arc_l2_asize{job=\"node-exporter\",kubernetes_node=~\"$node\"}",
          "format": "time_series",
          "hide": false,
          "interval": "",
          "intervalFactor": 2,
          "legendFormat": "asize",
          "range": true,
          "refId": "I",
          "step": 2,
          "target": ""
        },
        {
          "datasource": {
            "type": "prometheus",
            "uid": "prometheus"
          },
          "editorMode": "code",
          "expr": "node_zfs_arc_l2_hdr_size{job=\"node-exporter\",kubernetes_node=~\"$node\"}",
          "format": "time_series",
          "intervalFactor": 2,
          "legendFormat": "metadata",
          "range": true,
          "refId": "D",
          "step": 2,
          "target": ""
        },
        {
          "datasource": {
            "type": "prometheus",
            "uid": "prometheus"
          },
          "editorMode": "code",
          "expr": "node_zfs_arc_l2_size{job=\"node-exporter\",kubernetes_node=~\"$node\"}",
          "format": "time_series",
          "hide": false,
          "interval": "",
          "intervalFactor": 2,
          "legendFormat": "size",
          "range": true,
          "refId": "B",
          "step": 2,
          "target": ""
        }
      ],
      "title": "ARC L2 - Size",
      "type": "timeseries"
    }
  ],
  "preload": false,
  "refresh": "10s",
  "schemaVersion": 41,
  "tags": [],
  "templating": {
    "list": [
      {
        "current": {
          "text": "m00nsrv",
          "value": "m00nsrv"
        },
        "datasource": "Prometheus",
        "definition": "label_values(node_exporter_build_info{job=~\"node-exporter\"},kubernetes_node)",
        "includeAll": false,
        "name": "node",
        "options": [],
        "query": {
          "qryType": 1,
          "query": "label_values(node_exporter_build_info{job=~\"node-exporter\"},kubernetes_node)",
          "refId": "PrometheusVariableQueryEditor-VariableQuery"
        },
        "refresh": 1,
        "regex": "",
        "sort": 1,
        "type": "query"
      }
    ]
  },
  "time": {
    "from": "now-30m",
    "to": "now"
  },
  "timepicker": {},
  "timezone": "browser",
  "title": "ZFS2",
  "uid": "YLum8s2ik2",
  "version": 18
}
